dbf/LICENSE
dbf/README.md
dbf/WHATSNEW
dbf/__init__.py
dbf/_index.py
dbf/bridge.py
dbf/constants.py
dbf/data_types.py
dbf/exceptions.py
dbf/index.py
dbf/pql.py
dbf/tables.py
dbf/test.py
dbf/utils.py
dbf-0.99.11.dist-info/METADATA
dbf-0.99.11.dist-info/WHEEL
dbf-0.99.11.dist-info/top_level.txt
dbf-0.99.11.dist-info/RECORD
